tinydbstorage/__init__.py
tinydbstorage/schema/__init__.py
tinydbstorage/schema/s3.py
tinydbstorage/storage/__init__.py
tinydbstorage/storage/file.py
tinydbstorage/storage/memory.py
tinydbstorage/storage/redis.py
tinydbstorage/storage/s3.py
tinydbstorage-0.1.0.dist-info/LICENSE
tinydbstorage-0.1.0.dist-info/METADATA
tinydbstorage-0.1.0.dist-info/WHEEL
tinydbstorage-0.1.0.dist-info/RECORD
