Metadata-Version: 2.1
Name: tinydbstorage
Version: 0.1.0
Summary: Additional tinydb storage
License: MIT
Author: Ferdina Kusumah
Author-email: ferdina.kusumah@gmail.com
Requires-Python: >=3.10,<4.0
Classifier: License :: OSI Approved :: MIT License
Classifier: Programming Language :: Python :: 3
Classifier: Programming Language :: Python :: 3.10
Classifier: Programming Language :: Python :: 3.11
Requires-Dist: boto3 (>=1.34.13,<2.0.0)
Requires-Dist: pydantic (>=2.5.3,<3.0.0)
Requires-Dist: python-dateutil (>=2.8.2,<3.0.0)
Requires-Dist: redis (>=5.0.1,<6.0.0)
Requires-Dist: tinydb (>=4.8.0,<5.0.0)
